cmip6_aws/__init__.py
cmip6_aws/cmip6_aws.py
cmip6_aws/common.py
cmip6_aws/main.py
cmip6_aws/data/index_md5.txt
cmip6_aws/data/index_v1.1_md5.txt
cmip6_aws/data/index_v1.2_md5.txt
cmip6_aws-0.0.6.dist-info/LICENSE
cmip6_aws-0.0.6.dist-info/METADATA
cmip6_aws-0.0.6.dist-info/WHEEL
cmip6_aws-0.0.6.dist-info/entry_points.txt
cmip6_aws-0.0.6.dist-info/top_level.txt
cmip6_aws-0.0.6.dist-info/RECORD
