Metadata-Version: 2.1
Name: cmip6_aws
Version: 0.0.6
Summary: download data from NASA Earth Exchange Global Daily Downscaled Projections (NEX-GDDP-CMIP6)
Author-email: advancehs <1019753743@qq.com>
License: MIT License
Project-URL: Homepage, https://github.com/advancehs/cmip6_aws
Keywords: cmip6_aws
Classifier: Intended Audience :: Developers
Classifier: License :: OSI Approved :: MIT License
Classifier: Natural Language :: English
Classifier: Programming Language :: Python :: 3.8
Classifier: Programming Language :: Python :: 3.9
Classifier: Programming Language :: Python :: 3.10
Classifier: Programming Language :: Python :: 3.11
Classifier: Programming Language :: Python :: 3.12
Requires-Python: >=3.8
License-File: LICENSE
Requires-Dist: pandas
Requires-Dist: xarray
Requires-Dist: pyinstaller
Requires-Dist: s3fs
Requires-Dist: urllib3 ==1.26.15
Requires-Dist: h5netcdf
Requires-Dist: h5py
Requires-Dist: cftime
Requires-Dist: netCDF4
Requires-Dist: scipy
Provides-Extra: all
Requires-Dist: cmip6-aws[extra] ; extra == 'all'
Provides-Extra: extra
Requires-Dist: pandas ; extra == 'extra'
